freewrite/__about__.py
freewrite/__init__.py
freewrite/main.py
freewrite-0.0.2.dist-info/METADATA
freewrite-0.0.2.dist-info/WHEEL
freewrite-0.0.2.dist-info/entry_points.txt
freewrite-0.0.2.dist-info/licenses/LICENSE.txt
freewrite-0.0.2.dist-info/RECORD
