Metadata-Version: 2.1
Name: freewrite
Version: 0.0.2
Summary: A textual-based tool for structurng **freewriting**.
Project-URL: Documentation, https://github.com/unknown/freewrite#readme
Project-URL: Issues, https://github.com/unknown/freewrite/issues
Project-URL: Source, https://github.com/unknown/freewrite
Author-email: MatJohaDH <MathiasJoha@gmail.com>
License-Expression: MIT
License-File: LICENSE.txt
Classifier: Development Status :: 4 - Beta
Classifier: Programming Language :: Python
Classifier: Programming Language :: Python :: 3.8
Classifier: Programming Language :: Python :: 3.9
Classifier: Programming Language :: Python :: 3.10
Classifier: Programming Language :: Python :: 3.11
Classifier: Programming Language :: Python :: 3.12
Classifier: Programming Language :: Python :: Implementation :: CPython
Classifier: Programming Language :: Python :: Implementation :: PyPy
Requires-Python: >=3.8
Requires-Dist: textual>=0.41.0
